httpscan.py
httpscan-0.3.3.dist-info/LICENSE
httpscan-0.3.3.dist-info/METADATA
httpscan-0.3.3.dist-info/WHEEL
httpscan-0.3.3.dist-info/entry_points.txt
httpscan-0.3.3.dist-info/top_level.txt
httpscan-0.3.3.dist-info/RECORD
