Metadata-Version: 2.1
Name: httpscan
Version: 0.3.3
Author: Sergey M
License: FREE FOR NON-COMMERCIAL USE
Project-URL: Repository, https://github.com/s3rgeym/httpscan.git
Classifier: Topic :: Internet
Requires-Python: >=3.11.0
License-File: LICENSE
Requires-Dist: pyyaml
Requires-Dist: aiohttp[speedups]
Requires-Dist: aiohttp-socks
Provides-Extra: dev
Requires-Dist: ruff ; extra == 'dev'
